pipcn/__about__.py
pipcn/__init__.py
pipcn/__main__.py
pipcn/cli/__init__.py
pipcn-0.0.5.dist-info/METADATA
pipcn-0.0.5.dist-info/WHEEL
pipcn-0.0.5.dist-info/entry_points.txt
pipcn-0.0.5.dist-info/licenses/LICENSE
pipcn-0.0.5.dist-info/RECORD
