Metadata-Version: 2.1
Name: pipcn
Version: 0.0.5
Summary: 快速、方便的使用pip的国内镜像源安装/更新包~
Project-URL: Documentation, https://github.com/xuanzhi33/pipcn#readme
Project-URL: Issues, https://github.com/xuanzhi33/pipcn/issues
Project-URL: Source, https://github.com/xuanzhi33/pipcn
Author-email: xuanzhi33 <xuanzhi33@qq.com>
License-Expression: GPL-3.0-only
License-File: LICENSE
Classifier: Development Status :: 4 - Beta
Classifier: Programming Language :: Python
Classifier: Programming Language :: Python :: 3.8
Classifier: Programming Language :: Python :: 3.9
Classifier: Programming Language :: Python :: 3.10
Classifier: Programming Language :: Python :: 3.11
Classifier: Programming Language :: Python :: 3.12
Classifier: Programming Language :: Python :: Implementation :: CPython
Classifier: Programming Language :: Python :: Implementation :: PyPy
Requires-Python: >=3.8
